Metadata-Version: 2.1
Name: nacos-sdk-python-customer
Version: 0.1.15
Summary: Python client for Nacos.
Home-page: https://github.com/nacos-group/nacos-sdk-python
Author: nacos
Author-email: 755063194@qq.com
License: Apache License 2.0
Project-URL: Documentation, https://github.com/nacos-group/nacos-sdk-python
Project-URL: Source, https://github.com/nacos-group/nacos-sdk-python
Project-URL: Nacos Open API Guide, https://nacos.io/en-us/docs/open-api.html
Keywords: nacos,nacos-sdk-python
Classifier: Topic :: Software Development :: Libraries :: Python Modules
Classifier: Operating System :: OS Independent
Classifier: Programming Language :: Python
Classifier: Programming Language :: Python :: 2.7
Classifier: Programming Language :: Python :: 3.6
Classifier: Programming Language :: Python :: 3.7
